visorRobot/__init__.py
visorRobot/visor.py
visorRobot07-0.0.1.dist-info/METADATA
visorRobot07-0.0.1.dist-info/WHEEL
visorRobot07-0.0.1.dist-info/top_level.txt
visorRobot07-0.0.1.dist-info/RECORD
